hydro_erosion/__init__.py
hydro_erosion/__main__.py
hydro_erosion/erodeLandscape.py
hydro_erosion/generateLandscape.py
hydro_erosion/utilities.py
hydro_erosion-0.2.0.dist-info/METADATA
hydro_erosion-0.2.0.dist-info/WHEEL
hydro_erosion-0.2.0.dist-info/licenses/LICENSE
hydro_erosion-0.2.0.dist-info/RECORD
