Metadata-Version: 2.1
Name: hydro_erosion
Version: 0.2.0
Summary: Model of rain eroding a landscape
Project-URL: Homepage, https://github.com/mfigurski80/HydroErosion/tree/master
Project-URL: Bug Tracker, https://github.com/mfigurski80/HydroErosion/issues
Author-email: Mikolaj Figurski <miko.f80@gmail.com>
License: Copyright (c) 2018 The Python Packaging Authority
License-File: LICENSE
Classifier: License :: OSI Approved :: MIT License
Classifier: Operating System :: OS Independent
Classifier: Programming Language :: Python :: 3
Requires-Python: >=3.7
Requires-Dist: numpy
